giphy/__init__.py
giphy/__main__.py
giphy/get_gif.py
simply_giphy_cli_nronnei-0.0.5.dist-info/LICENSE
simply_giphy_cli_nronnei-0.0.5.dist-info/METADATA
simply_giphy_cli_nronnei-0.0.5.dist-info/WHEEL
simply_giphy_cli_nronnei-0.0.5.dist-info/top_level.txt
simply_giphy_cli_nronnei-0.0.5.dist-info/RECORD
