Metadata-Version: 2.1
Name: simply-giphy-cli-nronnei
Version: 0.0.5
Summary: A simple python-based CLI for searching Giphy
Home-page: UNKNOWN
Author: Nick Ronnei
Author-email: nronnei@gmail.com
License: UNKNOWN
Platform: UNKNOWN
Classifier: Programming Language :: Python :: 3
Classifier: License :: OSI Approved :: MIT License
Classifier: Operating System :: OS Independent
Requires-Python: >=3.6
Requires-Dist: certifi (==2020.4.5.1)
Requires-Dist: giphy-client (==1.0.0)
Requires-Dist: pyperclip (==1.8.0)
Requires-Dist: python-dateutil (==2.8.1)
Requires-Dist: six (==1.14.0)
Requires-Dist: urllib3 (==1.25.9)
